circuitpython_jled-1.0.5.dist-info/licenses/LICENSE
jled/__init__.py
jled/hal_pwm_circuitpython.py
jled/hal_pwm_micropython.py
jled/hal_time_circuitpython.py
jled/hal_time_micropython.py
jled/jled.py
jled/jled_sequence.py
jled/play.py
jled/python_pwm_hal.py
jled/python_time_hal.py
circuitpython_jled-1.0.5.dist-info/METADATA
circuitpython_jled-1.0.5.dist-info/WHEEL
circuitpython_jled-1.0.5.dist-info/top_level.txt
circuitpython_jled-1.0.5.dist-info/RECORD
