Metadata-Version: 2.4
Name: circuitpython-jled
Version: 1.0.5
Summary: Non-blocking LED controlling library
Author-email: Jan Delgado <jdelgado@gmx.net>
License: MIT
Project-URL: Homepage, https://github.com/jandelgado/jled-circuitpython
Keywords: adafruit,blinka,circuitpython,micropython,jled
Classifier: Intended Audience :: Developers
Classifier: Topic :: Software Development :: Libraries
Classifier: Topic :: Software Development :: Embedded Systems
Classifier: Topic :: System :: Hardware
Classifier: License :: OSI Approved :: MIT License
Classifier: Programming Language :: Python :: 3
License-File: LICENSE
Provides-Extra: optional
Requires-Dist: pytest==7.*; extra == "optional"
Requires-Dist: pytest-cov==4.*; extra == "optional"
Requires-Dist: mpremote; extra == "optional"
Requires-Dist: mpy-cross; extra == "optional"
Requires-Dist: sphinx==5.*; extra == "optional"
Requires-Dist: sphinx_rtd_theme==1.*; extra == "optional"
Dynamic: license-file
